[
  {
    "ContainingType": "backend.Controllers.AdminController",
    "Method": "CreateAd",
    "RelativePath": "api/Admin/ads",
    "HttpMethod": "POST",
    "IsController": true,
    "Order": 0,
    "Parameters": [
      {
        "Name": "req",
        "Type": "backend.DTO.AdRequest",
        "IsRequired": true
      }
    ],
    "ReturnTypes": []
  },
  {
    "ContainingType": "backend.Controllers.AdminController",
    "Method": "UpdateAd",
    "RelativePath": "api/Admin/ads/{id}",
    "HttpMethod": "PUT",
    "IsController": true,
    "Order": 0,
    "Parameters": [
      {
        "Name": "id",
        "Type": "System.Int32",
        "IsRequired": true
      },
      {
        "Name": "req",
        "Type": "backend.DTO.AdRequest",
        "IsRequired": true
      }
    ],
    "ReturnTypes": []
  },
  {
    "ContainingType": "backend.Controllers.AdminController",
    "Method": "DeleteAd",
    "RelativePath": "api/Admin/ads/{id}",
    "HttpMethod": "DELETE",
    "IsController": true,
    "Order": 0,
    "Parameters": [
      {
        "Name": "id",
        "Type": "System.Int32",
        "IsRequired": true
      }
    ],
    "ReturnTypes": []
  },
  {
    "ContainingType": "backend.Controllers.AdminController",
    "Method": "ToggleAdStatus",
    "RelativePath": "api/Admin/ads/{id}/toggle",
    "HttpMethod": "PUT",
    "IsController": true,
    "Order": 0,
    "Parameters": [
      {
        "Name": "id",
        "Type": "System.Int32",
        "IsRequired": true
      }
    ],
    "ReturnTypes": []
  },
  {
    "ContainingType": "backend.Controllers.AdminController",
    "Method": "GetActiveAds",
    "RelativePath": "api/Admin/ads/active",
    "HttpMethod": "GET",
    "IsController": true,
    "Order": 0,
    "Parameters": [
      {
        "Name": "position",
        "Type": "System.String",
        "IsRequired": false
      }
    ],
    "ReturnTypes": []
  },
  {
    "ContainingType": "backend.Controllers.AdminController",
    "Method": "GetAllAds",
    "RelativePath": "api/Admin/ads/all",
    "HttpMethod": "GET",
    "IsController": true,
    "Order": 0,
    "Parameters": [
      {
        "Name": "page",
        "Type": "System.Int32",
        "IsRequired": false
      },
      {
        "Name": "pageSize",
        "Type": "System.Int32",
        "IsRequired": false
      },
      {
        "Name": "keyword",
        "Type": "System.String",
        "IsRequired": false
      }
    ],
    "ReturnTypes": []
  },
  {
    "ContainingType": "backend.Controllers.AdminController",
    "Method": "GetReports",
    "RelativePath": "api/Admin/reports",
    "HttpMethod": "GET",
    "IsController": true,
    "Order": 0,
    "Parameters": [],
    "ReturnTypes": []
  },
  {
    "ContainingType": "backend.Controllers.AdminController",
    "Method": "UpdateReportStatus",
    "RelativePath": "api/Admin/reports/{id}/status",
    "HttpMethod": "PUT",
    "IsController": true,
    "Order": 0,
    "Parameters": [
      {
        "Name": "id",
        "Type": "System.Int32",
        "IsRequired": true
      },
      {
        "Name": "req",
        "Type": "backend.DTO.UpdateReportStatusReq",
        "IsRequired": true
      }
    ],
    "ReturnTypes": []
  },
  {
    "ContainingType": "backend.Controllers.AdminController",
    "Method": "GetSystemStats",
    "RelativePath": "api/Admin/statistics",
    "HttpMethod": "GET",
    "IsController": true,
    "Order": 0,
    "Parameters": [],
    "ReturnTypes": []
  },
  {
    "ContainingType": "backend.Controllers.AdminController",
    "Method": "UpgradeRole",
    "RelativePath": "api/Admin/upgrade-role",
    "HttpMethod": "PUT",
    "IsController": true,
    "Order": 0,
    "Parameters": [
      {
        "Name": "req",
        "Type": "backend.DTO.ChangeRoleRequest",
        "IsRequired": true
      }
    ],
    "ReturnTypes": []
  },
  {
    "ContainingType": "backend.Controllers.AuthController",
    "Method": "ForgotPassword",
    "RelativePath": "api/Auth/ForgotPassword",
    "HttpMethod": "POST",
    "IsController": true,
    "Order": 0,
    "Parameters": [
      {
        "Name": "req",
        "Type": "backend.DTO.ForgotPasswordRequest",
        "IsRequired": true
      }
    ],
    "ReturnTypes": []
  },
  {
    "ContainingType": "backend.Controllers.AuthController",
    "Method": "Login",
    "RelativePath": "api/Auth/login",
    "HttpMethod": "POST",
    "IsController": true,
    "Order": 0,
    "Parameters": [
      {
        "Name": "req",
        "Type": "backend.DTO.LoginRequest",
        "IsRequired": true
      }
    ],
    "ReturnTypes": []
  },
  {
    "ContainingType": "backend.Controllers.AuthController",
    "Method": "Logout",
    "RelativePath": "api/Auth/LogOut",
    "HttpMethod": "POST",
    "IsController": true,
    "Order": 0,
    "Parameters": [],
    "ReturnTypes": []
  },
  {
    "ContainingType": "backend.Controllers.AuthController",
    "Method": "RefreshToken",
    "RelativePath": "api/Auth/RefreshToken",
    "HttpMethod": "POST",
    "IsController": true,
    "Order": 0,
    "Parameters": [],
    "ReturnTypes": []
  },
  {
    "ContainingType": "backend.Controllers.AuthController",
    "Method": "Register",
    "RelativePath": "api/Auth/Register",
    "HttpMethod": "POST",
    "IsController": true,
    "Order": 0,
    "Parameters": [
      {
        "Name": "req",
        "Type": "backend.DTO.RegisterRequest",
        "IsRequired": true
      }
    ],
    "ReturnTypes": []
  },
  {
    "ContainingType": "backend.Controllers.AuthController",
    "Method": "ResetPassword",
    "RelativePath": "api/Auth/ResetPassword",
    "HttpMethod": "POST",
    "IsController": true,
    "Order": 0,
    "Parameters": [
      {
        "Name": "req",
        "Type": "backend.DTO.ResetPasswordRequest",
        "IsRequired": true
      }
    ],
    "ReturnTypes": []
  },
  {
    "ContainingType": "backend.Controllers.BookingController",
    "Method": "CancelBooking",
    "RelativePath": "api/Booking/{id}/cancel",
    "HttpMethod": "PUT",
    "IsController": true,
    "Order": 0,
    "Parameters": [
      {
        "Name": "id",
        "Type": "System.Int32",
        "IsRequired": true
      }
    ],
    "ReturnTypes": []
  },
  {
    "ContainingType": "backend.Controllers.BookingController",
    "Method": "UpdateBookingStatus",
    "RelativePath": "api/Booking/{id}/status",
    "HttpMethod": "PUT",
    "IsController": true,
    "Order": 0,
    "Parameters": [
      {
        "Name": "id",
        "Type": "System.Int32",
        "IsRequired": true
      },
      {
        "Name": "req",
        "Type": "backend.DTO.UpdateBookingStatusReq",
        "IsRequired": true
      }
    ],
    "ReturnTypes": []
  },
  {
    "ContainingType": "backend.Controllers.BookingController",
    "Method": "CreateBooking",
    "RelativePath": "api/Booking/create",
    "HttpMethod": "POST",
    "IsController": true,
    "Order": 0,
    "Parameters": [
      {
        "Name": "req",
        "Type": "backend.DTO.BookingRequest",
        "IsRequired": true
      }
    ],
    "ReturnTypes": []
  },
  {
    "ContainingType": "backend.Controllers.BookingController",
    "Method": "GetOwnerDashboardStats",
    "RelativePath": "api/Booking/dashboard-stats",
    "HttpMethod": "GET",
    "IsController": true,
    "Order": 0,
    "Parameters": [],
    "ReturnTypes": []
  },
  {
    "ContainingType": "backend.Controllers.BookingController",
    "Method": "GetMyBookings",
    "RelativePath": "api/Booking/my-bookings",
    "HttpMethod": "GET",
    "IsController": true,
    "Order": 0,
    "Parameters": [],
    "ReturnTypes": []
  },
  {
    "ContainingType": "backend.Controllers.BookingController",
    "Method": "GetReceivedBookings",
    "RelativePath": "api/Booking/received-bookings",
    "HttpMethod": "GET",
    "IsController": true,
    "Order": 0,
    "Parameters": [],
    "ReturnTypes": []
  },
  {
    "ContainingType": "backend.Controllers.FavoriteController",
    "Method": "GetMyFavorites",
    "RelativePath": "api/Favorite/my-favorites",
    "HttpMethod": "GET",
    "IsController": true,
    "Order": 0,
    "Parameters": [
      {
        "Name": "page",
        "Type": "System.Int32",
        "IsRequired": false
      },
      {
        "Name": "pageSize",
        "Type": "System.Int32",
        "IsRequired": false
      }
    ],
    "ReturnTypes": []
  },
  {
    "ContainingType": "backend.Controllers.FavoriteController",
    "Method": "Toggle",
    "RelativePath": "api/Favorite/toggle",
    "HttpMethod": "POST",
    "IsController": true,
    "Order": 0,
    "Parameters": [
      {
        "Name": "req",
        "Type": "backend.DTO.FavoriteRequest",
        "IsRequired": true
      }
    ],
    "ReturnTypes": []
  },
  {
    "ContainingType": "backend.Controllers.HomeController",
    "Method": "Hottel",
    "RelativePath": "api/Home/hottel",
    "HttpMethod": "GET",
    "IsController": true,
    "Order": 0,
    "Parameters": [
      {
        "Name": "tourist_place_id",
        "Type": "System.Int32",
        "IsRequired": false
      }
    ],
    "ReturnTypes": []
  },
  {
    "ContainingType": "backend.Controllers.HomeController",
    "Method": "Index",
    "RelativePath": "api/Home/index",
    "HttpMethod": "GET",
    "IsController": true,
    "Order": 0,
    "Parameters": [],
    "ReturnTypes": []
  },
  {
    "ContainingType": "backend.Controllers.HomeController",
    "Method": "Tours",
    "RelativePath": "api/Home/tour",
    "HttpMethod": "GET",
    "IsController": true,
    "Order": 0,
    "Parameters": [
      {
        "Name": "tourist_area_id",
        "Type": "System.Int32",
        "IsRequired": false
      }
    ],
    "ReturnTypes": []
  },
  {
    "ContainingType": "backend.Controllers.HomeController",
    "Method": "Tourist_Place",
    "RelativePath": "api/Home/Tourist_Place",
    "HttpMethod": "GET",
    "IsController": true,
    "Order": 0,
    "Parameters": [
      {
        "Name": "tourist_area_id",
        "Type": "System.Int32",
        "IsRequired": false
      }
    ],
    "ReturnTypes": []
  },
  {
    "ContainingType": "backend.Controllers.HotelController",
    "Method": "CreateHotel",
    "RelativePath": "api/Hotel",
    "HttpMethod": "POST",
    "IsController": true,
    "Order": 0,
    "Parameters": [
      {
        "Name": "req",
        "Type": "backend.DTO.HotelRequest",
        "IsRequired": true
      }
    ],
    "ReturnTypes": []
  },
  {
    "ContainingType": "backend.Controllers.HotelController",
    "Method": "AddRoom",
    "RelativePath": "api/Hotel/{hotelId}/rooms",
    "HttpMethod": "POST",
    "IsController": true,
    "Order": 0,
    "Parameters": [
      {
        "Name": "hotelId",
        "Type": "System.Int32",
        "IsRequired": true
      },
      {
        "Name": "req",
        "Type": "backend.DTO.RoomRequest",
        "IsRequired": true
      }
    ],
    "ReturnTypes": []
  },
  {
    "ContainingType": "backend.Controllers.HotelController",
    "Method": "UpdateHotel",
    "RelativePath": "api/Hotel/{id}",
    "HttpMethod": "PUT",
    "IsController": true,
    "Order": 0,
    "Parameters": [
      {
        "Name": "id",
        "Type": "System.Int32",
        "IsRequired": true
      },
      {
        "Name": "req",
        "Type": "backend.DTO.HotelRequest",
        "IsRequired": true
      }
    ],
    "ReturnTypes": []
  },
  {
    "ContainingType": "backend.Controllers.HotelController",
    "Method": "DeleteHotel",
    "RelativePath": "api/Hotel/{id}",
    "HttpMethod": "DELETE",
    "IsController": true,
    "Order": 0,
    "Parameters": [
      {
        "Name": "id",
        "Type": "System.Int32",
        "IsRequired": true
      }
    ],
    "ReturnTypes": []
  },
  {
    "ContainingType": "backend.Controllers.HotelController",
    "Method": "GetAllHotelsForAdmin",
    "RelativePath": "api/Hotel/admin/all",
    "HttpMethod": "GET",
    "IsController": true,
    "Order": 0,
    "Parameters": [
      {
        "Name": "page",
        "Type": "System.Int32",
        "IsRequired": false
      },
      {
        "Name": "pageSize",
        "Type": "System.Int32",
        "IsRequired": false
      },
      {
        "Name": "keyword",
        "Type": "System.String",
        "IsRequired": false
      },
      {
        "Name": "status",
        "Type": "System.String",
        "IsRequired": false
      }
    ],
    "ReturnTypes": []
  },
  {
    "ContainingType": "backend.Controllers.HotelController",
    "Method": "GetAllPendingHotels",
    "RelativePath": "api/Hotel/admin/pending",
    "HttpMethod": "GET",
    "IsController": true,
    "Order": 0,
    "Parameters": [
      {
        "Name": "page",
        "Type": "System.Int32",
        "IsRequired": false
      },
      {
        "Name": "pageSize",
        "Type": "System.Int32",
        "IsRequired": false
      }
    ],
    "ReturnTypes": []
  },
  {
    "ContainingType": "backend.Controllers.HotelController",
    "Method": "ApproveHotel",
    "RelativePath": "api/Hotel/approve/{id}",
    "HttpMethod": "PUT",
    "IsController": true,
    "Order": 0,
    "Parameters": [
      {
        "Name": "id",
        "Type": "System.Int32",
        "IsRequired": true
      },
      {
        "Name": "req",
        "Type": "backend.DTO.ApprovalRequest",
        "IsRequired": true
      }
    ],
    "ReturnTypes": []
  },
  {
    "ContainingType": "backend.Controllers.HotelController",
    "Method": "GetDetail",
    "RelativePath": "api/Hotel/detail",
    "HttpMethod": "GET",
    "IsController": true,
    "Order": 0,
    "Parameters": [
      {
        "Name": "id",
        "Type": "System.Int32",
        "IsRequired": false
      }
    ],
    "ReturnTypes": []
  },
  {
    "ContainingType": "backend.Controllers.HotelController",
    "Method": "GetList",
    "RelativePath": "api/Hotel/list",
    "HttpMethod": "GET",
    "IsController": true,
    "Order": 0,
    "Parameters": [
      {
        "Name": "page",
        "Type": "System.Int32",
        "IsRequired": false
      },
      {
        "Name": "pageSize",
        "Type": "System.Int32",
        "IsRequired": false
      }
    ],
    "ReturnTypes": []
  },
  {
    "ContainingType": "backend.Controllers.HotelController",
    "Method": "GetMyHotels",
    "RelativePath": "api/Hotel/my-hotels",
    "HttpMethod": "GET",
    "IsController": true,
    "Order": 0,
    "Parameters": [
      {
        "Name": "page",
        "Type": "System.Int32",
        "IsRequired": false
      },
      {
        "Name": "pageSize",
        "Type": "System.Int32",
        "IsRequired": false
      },
      {
        "Name": "keyword",
        "Type": "System.String",
        "IsRequired": false
      },
      {
        "Name": "status",
        "Type": "System.String",
        "IsRequired": false
      }
    ],
    "ReturnTypes": []
  },
  {
    "ContainingType": "backend.Controllers.HotelController",
    "Method": "UpdateRoom",
    "RelativePath": "api/Hotel/rooms/{roomId}",
    "HttpMethod": "PUT",
    "IsController": true,
    "Order": 0,
    "Parameters": [
      {
        "Name": "roomId",
        "Type": "System.Int32",
        "IsRequired": true
      },
      {
        "Name": "req",
        "Type": "backend.DTO.RoomRequest",
        "IsRequired": true
      }
    ],
    "ReturnTypes": []
  },
  {
    "ContainingType": "backend.Controllers.HotelController",
    "Method": "DeleteHotelRoom",
    "RelativePath": "api/Hotel/rooms/{roomId}",
    "HttpMethod": "DELETE",
    "IsController": true,
    "Order": 0,
    "Parameters": [
      {
        "Name": "roomId",
        "Type": "System.Int32",
        "IsRequired": true
      }
    ],
    "ReturnTypes": []
  },
  {
    "ContainingType": "backend.Controllers.ImageController",
    "Method": "DeleteImage",
    "RelativePath": "api/Image/{id}",
    "HttpMethod": "DELETE",
    "IsController": true,
    "Order": 0,
    "Parameters": [
      {
        "Name": "id",
        "Type": "System.Int32",
        "IsRequired": true
      }
    ],
    "ReturnTypes": []
  },
  {
    "ContainingType": "backend.Controllers.ImageController",
    "Method": "SaveImageLink",
    "RelativePath": "api/Image/save-link",
    "HttpMethod": "POST",
    "IsController": true,
    "Order": 0,
    "Parameters": [
      {
        "Name": "req",
        "Type": "backend.DTO.ImageLinkRequest",
        "IsRequired": true
      }
    ],
    "ReturnTypes": []
  },
  {
    "ContainingType": "backend.Controllers.ImageController",
    "Method": "SetCoverImage",
    "RelativePath": "api/Image/set-cover/{id}",
    "HttpMethod": "PUT",
    "IsController": true,
    "Order": 0,
    "Parameters": [
      {
        "Name": "id",
        "Type": "System.Int32",
        "IsRequired": true
      },
      {
        "Name": "entityType",
        "Type": "System.String",
        "IsRequired": false
      },
      {
        "Name": "entityId",
        "Type": "System.Int32",
        "IsRequired": false
      }
    ],
    "ReturnTypes": []
  },
  {
    "ContainingType": "backend.Controllers.InteractionController",
    "Method": "GetMyReviews",
    "RelativePath": "api/Interaction/my-reviews",
    "HttpMethod": "GET",
    "IsController": true,
    "Order": 0,
    "Parameters": [
      {
        "Name": "page",
        "Type": "System.Int32",
        "IsRequired": false
      },
      {
        "Name": "pageSize",
        "Type": "System.Int32",
        "IsRequired": false
      }
    ],
    "ReturnTypes": []
  },
  {
    "ContainingType": "backend.Controllers.MarkerController",
    "Method": "CreateMarker",
    "RelativePath": "api/Marker",
    "HttpMethod": "POST",
    "IsController": true,
    "Order": 0,
    "Parameters": [
      {
        "Name": "req",
        "Type": "backend.DTO.MarkerRequest",
        "IsRequired": true
      }
    ],
    "ReturnTypes": []
  },
  {
    "ContainingType": "backend.Controllers.MarkerController",
    "Method": "UpdateMarker",
    "RelativePath": "api/Marker/{id}",
    "HttpMethod": "PUT",
    "IsController": true,
    "Order": 0,
    "Parameters": [
      {
        "Name": "id",
        "Type": "System.Int32",
        "IsRequired": true
      },
      {
        "Name": "req",
        "Type": "backend.DTO.MarkerRequest",
        "IsRequired": true
      }
    ],
    "ReturnTypes": []
  },
  {
    "ContainingType": "backend.Controllers.MarkerController",
    "Method": "DeleteMarker",
    "RelativePath": "api/Marker/{id}",
    "HttpMethod": "DELETE",
    "IsController": true,
    "Order": 0,
    "Parameters": [
      {
        "Name": "id",
        "Type": "System.Int32",
        "IsRequired": true
      }
    ],
    "ReturnTypes": []
  },
  {
    "ContainingType": "backend.Controllers.MarkerController",
    "Method": "AdminDeleteMarker",
    "RelativePath": "api/Marker/admin/{id}",
    "HttpMethod": "DELETE",
    "IsController": true,
    "Order": 0,
    "Parameters": [
      {
        "Name": "id",
        "Type": "System.Int32",
        "IsRequired": true
      }
    ],
    "ReturnTypes": []
  },
  {
    "ContainingType": "backend.Controllers.MarkerController",
    "Method": "GetAllMarkersForAdmin",
    "RelativePath": "api/Marker/admin/all",
    "HttpMethod": "GET",
    "IsController": true,
    "Order": 0,
    "Parameters": [],
    "ReturnTypes": []
  },
  {
    "ContainingType": "backend.Controllers.MarkerController",
    "Method": "GetMyMarkers",
    "RelativePath": "api/Marker/me",
    "HttpMethod": "GET",
    "IsController": true,
    "Order": 0,
    "Parameters": [
      {
        "Name": "keyword",
        "Type": "System.String",
        "IsRequired": false
      }
    ],
    "ReturnTypes": []
  },
  {
    "ContainingType": "backend.Controllers.MarkerController",
    "Method": "GetPublicMarkers",
    "RelativePath": "api/Marker/public",
    "HttpMethod": "GET",
    "IsController": true,
    "Order": 0,
    "Parameters": [],
    "ReturnTypes": []
  },
  {
    "ContainingType": "backend.Controllers.NotificationController",
    "Method": "GetMyNotifications",
    "RelativePath": "api/Notification",
    "HttpMethod": "GET",
    "IsController": true,
    "Order": 0,
    "Parameters": [],
    "ReturnTypes": []
  },
  {
    "ContainingType": "backend.Controllers.NotificationController",
    "Method": "MarkAsRead",
    "RelativePath": "api/Notification/{id}/read",
    "HttpMethod": "PUT",
    "IsController": true,
    "Order": 0,
    "Parameters": [
      {
        "Name": "id",
        "Type": "System.Int32",
        "IsRequired": true
      }
    ],
    "ReturnTypes": []
  },
  {
    "ContainingType": "backend.Controllers.ProfileController",
    "Method": "ChangePassword",
    "RelativePath": "api/Profile/change-password",
    "HttpMethod": "PUT",
    "IsController": true,
    "Order": 0,
    "Parameters": [
      {
        "Name": "req",
        "Type": "backend.DTO.ChangePasswordRequest",
        "IsRequired": true
      }
    ],
    "ReturnTypes": []
  },
  {
    "ContainingType": "backend.Controllers.ProfileController",
    "Method": "SubmitFeedback",
    "RelativePath": "api/Profile/feedback",
    "HttpMethod": "POST",
    "IsController": true,
    "Order": 0,
    "Parameters": [
      {
        "Name": "req",
        "Type": "backend.DTO.FeedbackRequest",
        "IsRequired": true
      }
    ],
    "ReturnTypes": []
  },
  {
    "ContainingType": "backend.Controllers.ProfileController",
    "Method": "GetMyProfile",
    "RelativePath": "api/Profile/me",
    "HttpMethod": "GET",
    "IsController": true,
    "Order": 0,
    "Parameters": [],
    "ReturnTypes": []
  },
  {
    "ContainingType": "backend.Controllers.ProfileController",
    "Method": "UpdateProfile",
    "RelativePath": "api/Profile/update",
    "HttpMethod": "PUT",
    "IsController": true,
    "Order": 0,
    "Parameters": [
      {
        "Name": "req",
        "Type": "backend.DTO.UpdateProfileRequest",
        "IsRequired": true
      }
    ],
    "ReturnTypes": []
  },
  {
    "ContainingType": "backend.Controllers.ReviewController",
    "Method": "PostReview",
    "RelativePath": "api/Review",
    "HttpMethod": "POST",
    "IsController": true,
    "Order": 0,
    "Parameters": [
      {
        "Name": "req",
        "Type": "backend.DTO.ReviewRequest",
        "IsRequired": true
      }
    ],
    "ReturnTypes": []
  },
  {
    "ContainingType": "backend.Controllers.ReviewController",
    "Method": "GetReviews",
    "RelativePath": "api/Review/{type}/{id}",
    "HttpMethod": "GET",
    "IsController": true,
    "Order": 0,
    "Parameters": [
      {
        "Name": "type",
        "Type": "System.String",
        "IsRequired": true
      },
      {
        "Name": "id",
        "Type": "System.Int32",
        "IsRequired": true
      }
    ],
    "ReturnTypes": []
  },
  {
    "ContainingType": "backend.Controllers.ReviewController",
    "Method": "GetOwnerReviewStats",
    "RelativePath": "api/Review/owner-stats",
    "HttpMethod": "GET",
    "IsController": true,
    "Order": 0,
    "Parameters": [],
    "ReturnTypes": []
  },
  {
    "ContainingType": "backend.Controllers.SearchController",
    "Method": "FilterData",
    "RelativePath": "api/Search/filter",
    "HttpMethod": "POST",
    "IsController": true,
    "Order": 0,
    "Parameters": [
      {
        "Name": "req",
        "Type": "backend.DTO.SearchFilterRequest",
        "IsRequired": true
      }
    ],
    "ReturnTypes": []
  },
  {
    "ContainingType": "backend.Controllers.TourController",
    "Method": "CreateTour",
    "RelativePath": "api/Tour",
    "HttpMethod": "POST",
    "IsController": true,
    "Order": 0,
    "Parameters": [
      {
        "Name": "req",
        "Type": "backend.DTO.TourRequest",
        "IsRequired": true
      }
    ],
    "ReturnTypes": []
  },
  {
    "ContainingType": "backend.Controllers.TourController",
    "Method": "UpdateTour",
    "RelativePath": "api/Tour/{id}",
    "HttpMethod": "PUT",
    "IsController": true,
    "Order": 0,
    "Parameters": [
      {
        "Name": "id",
        "Type": "System.Int32",
        "IsRequired": true
      },
      {
        "Name": "req",
        "Type": "backend.DTO.TourRequest",
        "IsRequired": true
      }
    ],
    "ReturnTypes": []
  },
  {
    "ContainingType": "backend.Controllers.TourController",
    "Method": "DeleteTour",
    "RelativePath": "api/Tour/{id}",
    "HttpMethod": "DELETE",
    "IsController": true,
    "Order": 0,
    "Parameters": [
      {
        "Name": "id",
        "Type": "System.Int32",
        "IsRequired": true
      }
    ],
    "ReturnTypes": []
  },
  {
    "ContainingType": "backend.Controllers.TourController",
    "Method": "AddDeparture",
    "RelativePath": "api/Tour/{tourId}/departures",
    "HttpMethod": "POST",
    "IsController": true,
    "Order": 0,
    "Parameters": [
      {
        "Name": "tourId",
        "Type": "System.Int32",
        "IsRequired": true
      },
      {
        "Name": "req",
        "Type": "backend.DTO.DepartureRequest",
        "IsRequired": true
      }
    ],
    "ReturnTypes": []
  },
  {
    "ContainingType": "backend.Controllers.TourController",
    "Method": "AddItinerary",
    "RelativePath": "api/Tour/{tourId}/itinerary",
    "HttpMethod": "POST",
    "IsController": true,
    "Order": 0,
    "Parameters": [
      {
        "Name": "tourId",
        "Type": "System.Int32",
        "IsRequired": true
      },
      {
        "Name": "req",
        "Type": "backend.DTO.TourItineraryRequest",
        "IsRequired": true
      }
    ],
    "ReturnTypes": []
  },
  {
    "ContainingType": "backend.Controllers.TourController",
    "Method": "GetAllToursForAdmin",
    "RelativePath": "api/Tour/admin/all",
    "HttpMethod": "GET",
    "IsController": true,
    "Order": 0,
    "Parameters": [
      {
        "Name": "page",
        "Type": "System.Int32",
        "IsRequired": false
      },
      {
        "Name": "pageSize",
        "Type": "System.Int32",
        "IsRequired": false
      },
      {
        "Name": "keyword",
        "Type": "System.String",
        "IsRequired": false
      },
      {
        "Name": "status",
        "Type": "System.String",
        "IsRequired": false
      }
    ],
    "ReturnTypes": []
  },
  {
    "ContainingType": "backend.Controllers.TourController",
    "Method": "GetAllPendingTours",
    "RelativePath": "api/Tour/admin/pending",
    "HttpMethod": "GET",
    "IsController": true,
    "Order": 0,
    "Parameters": [
      {
        "Name": "page",
        "Type": "System.Int32",
        "IsRequired": false
      },
      {
        "Name": "pageSize",
        "Type": "System.Int32",
        "IsRequired": false
      }
    ],
    "ReturnTypes": []
  },
  {
    "ContainingType": "backend.Controllers.TourController",
    "Method": "ApproveTour",
    "RelativePath": "api/Tour/approve/{id}",
    "HttpMethod": "PUT",
    "IsController": true,
    "Order": 0,
    "Parameters": [
      {
        "Name": "id",
        "Type": "System.Int32",
        "IsRequired": true
      },
      {
        "Name": "req",
        "Type": "backend.DTO.ApprovalRequest",
        "IsRequired": true
      }
    ],
    "ReturnTypes": []
  },
  {
    "ContainingType": "backend.Controllers.TourController",
    "Method": "UpdateDeparture",
    "RelativePath": "api/Tour/departures/{id}",
    "HttpMethod": "PUT",
    "IsController": true,
    "Order": 0,
    "Parameters": [
      {
        "Name": "id",
        "Type": "System.Int32",
        "IsRequired": true
      },
      {
        "Name": "req",
        "Type": "backend.DTO.DepartureRequest",
        "IsRequired": true
      }
    ],
    "ReturnTypes": []
  },
  {
    "ContainingType": "backend.Controllers.TourController",
    "Method": "DeleteDeparture",
    "RelativePath": "api/Tour/departures/{id}",
    "HttpMethod": "DELETE",
    "IsController": true,
    "Order": 0,
    "Parameters": [
      {
        "Name": "id",
        "Type": "System.Int32",
        "IsRequired": true
      }
    ],
    "ReturnTypes": []
  },
  {
    "ContainingType": "backend.Controllers.TourController",
    "Method": "DetailTour",
    "RelativePath": "api/Tour/detail",
    "HttpMethod": "GET",
    "IsController": true,
    "Order": 0,
    "Parameters": [
      {
        "Name": "id",
        "Type": "System.Int32",
        "IsRequired": false
      }
    ],
    "ReturnTypes": []
  },
  {
    "ContainingType": "backend.Controllers.TourController",
    "Method": "UpdateItinerary",
    "RelativePath": "api/Tour/itinerary/{id}",
    "HttpMethod": "PUT",
    "IsController": true,
    "Order": 0,
    "Parameters": [
      {
        "Name": "id",
        "Type": "System.Int32",
        "IsRequired": true
      },
      {
        "Name": "req",
        "Type": "backend.DTO.TourItineraryRequest",
        "IsRequired": true
      }
    ],
    "ReturnTypes": []
  },
  {
    "ContainingType": "backend.Controllers.TourController",
    "Method": "DeleteItinerary",
    "RelativePath": "api/Tour/itinerary/{id}",
    "HttpMethod": "DELETE",
    "IsController": true,
    "Order": 0,
    "Parameters": [
      {
        "Name": "id",
        "Type": "System.Int32",
        "IsRequired": true
      }
    ],
    "ReturnTypes": []
  },
  {
    "ContainingType": "backend.Controllers.TourController",
    "Method": "GetMyTours",
    "RelativePath": "api/Tour/my-tours",
    "HttpMethod": "GET",
    "IsController": true,
    "Order": 0,
    "Parameters": [
      {
        "Name": "page",
        "Type": "System.Int32",
        "IsRequired": false
      },
      {
        "Name": "pageSize",
        "Type": "System.Int32",
        "IsRequired": false
      },
      {
        "Name": "keyword",
        "Type": "System.String",
        "IsRequired": false
      },
      {
        "Name": "status",
        "Type": "System.String",
        "IsRequired": false
      }
    ],
    "ReturnTypes": []
  },
  {
    "ContainingType": "backend.Controllers.TourController",
    "Method": "GetTour",
    "RelativePath": "api/Tour/tour",
    "HttpMethod": "GET",
    "IsController": true,
    "Order": 0,
    "Parameters": [
      {
        "Name": "page",
        "Type": "System.Int32",
        "IsRequired": false
      },
      {
        "Name": "pageSize",
        "Type": "System.Int32",
        "IsRequired": false
      }
    ],
    "ReturnTypes": []
  },
  {
    "ContainingType": "backend.Controllers.TouristAreaController",
    "Method": "CreateTouristArea",
    "RelativePath": "api/TouristArea",
    "HttpMethod": "POST",
    "IsController": true,
    "Order": 0,
    "Parameters": [
      {
        "Name": "request",
        "Type": "backend.DTO.TouristAreaRequest",
        "IsRequired": true
      }
    ],
    "ReturnTypes": []
  },
  {
    "ContainingType": "backend.Controllers.TouristAreaController",
    "Method": "UpdateTouristArea",
    "RelativePath": "api/TouristArea/{id}",
    "HttpMethod": "PUT",
    "IsController": true,
    "Order": 0,
    "Parameters": [
      {
        "Name": "id",
        "Type": "System.Int32",
        "IsRequired": true
      },
      {
        "Name": "request",
        "Type": "backend.DTO.TouristAreaRequest",
        "IsRequired": true
      }
    ],
    "ReturnTypes": []
  },
  {
    "ContainingType": "backend.Controllers.TouristAreaController",
    "Method": "DeleteTouristArea",
    "RelativePath": "api/TouristArea/{id}",
    "HttpMethod": "DELETE",
    "IsController": true,
    "Order": 0,
    "Parameters": [
      {
        "Name": "id",
        "Type": "System.Int32",
        "IsRequired": true
      }
    ],
    "ReturnTypes": []
  },
  {
    "ContainingType": "backend.Controllers.TouristAreaController",
    "Method": "GetAllTouristAreasForAdmin",
    "RelativePath": "api/TouristArea/admin/all",
    "HttpMethod": "GET",
    "IsController": true,
    "Order": 0,
    "Parameters": [
      {
        "Name": "page",
        "Type": "System.Int32",
        "IsRequired": false
      },
      {
        "Name": "pageSize",
        "Type": "System.Int32",
        "IsRequired": false
      },
      {
        "Name": "keyword",
        "Type": "System.String",
        "IsRequired": false
      },
      {
        "Name": "status",
        "Type": "System.String",
        "IsRequired": false
      }
    ],
    "ReturnTypes": []
  },
  {
    "ContainingType": "backend.Controllers.TouristAreaController",
    "Method": "GetAllPendingTouristAreas",
    "RelativePath": "api/TouristArea/admin/pending",
    "HttpMethod": "GET",
    "IsController": true,
    "Order": 0,
    "Parameters": [
      {
        "Name": "page",
        "Type": "System.Int32",
        "IsRequired": false
      },
      {
        "Name": "pageSize",
        "Type": "System.Int32",
        "IsRequired": false
      }
    ],
    "ReturnTypes": []
  },
  {
    "ContainingType": "backend.Controllers.TouristAreaController",
    "Method": "GetAllForDropdown",
    "RelativePath": "api/TouristArea/all-dropdown",
    "HttpMethod": "GET",
    "IsController": true,
    "Order": 0,
    "Parameters": [],
    "ReturnTypes": []
  },
  {
    "ContainingType": "backend.Controllers.TouristAreaController",
    "Method": "ApproveTouristArea",
    "RelativePath": "api/TouristArea/approve/{id}",
    "HttpMethod": "PUT",
    "IsController": true,
    "Order": 0,
    "Parameters": [
      {
        "Name": "id",
        "Type": "System.Int32",
        "IsRequired": true
      },
      {
        "Name": "req",
        "Type": "backend.DTO.ApprovalRequest",
        "IsRequired": true
      }
    ],
    "ReturnTypes": []
  },
  {
    "ContainingType": "backend.Controllers.TouristAreaController",
    "Method": "DetailTouristArea",
    "RelativePath": "api/TouristArea/DetailTouristArea",
    "HttpMethod": "POST",
    "IsController": true,
    "Order": 0,
    "Parameters": [
      {
        "Name": "req",
        "Type": "backend.DTO.TourismProductDetailRequest",
        "IsRequired": true
      }
    ],
    "ReturnTypes": []
  },
  {
    "ContainingType": "backend.Controllers.TouristAreaController",
    "Method": "DetailTouristAreaUser",
    "RelativePath": "api/TouristArea/DetailTouristAreaUser",
    "HttpMethod": "POST",
    "IsController": true,
    "Order": 0,
    "Parameters": [
      {
        "Name": "req",
        "Type": "backend.DTO.TourismProductDetailRequest",
        "IsRequired": true
      }
    ],
    "ReturnTypes": []
  },
  {
    "ContainingType": "backend.Controllers.TouristAreaController",
    "Method": "GetMyTouristAreas",
    "RelativePath": "api/TouristArea/my-areas",
    "HttpMethod": "GET",
    "IsController": true,
    "Order": 0,
    "Parameters": [
      {
        "Name": "page",
        "Type": "System.Int32",
        "IsRequired": false
      },
      {
        "Name": "pageSize",
        "Type": "System.Int32",
        "IsRequired": false
      },
      {
        "Name": "keyword",
        "Type": "System.String",
        "IsRequired": false
      },
      {
        "Name": "status",
        "Type": "System.String",
        "IsRequired": false
      }
    ],
    "ReturnTypes": []
  },
  {
    "ContainingType": "backend.Controllers.TouristAreaController",
    "Method": "tourist_area",
    "RelativePath": "api/TouristArea/tourist_area",
    "HttpMethod": "GET",
    "IsController": true,
    "Order": 0,
    "Parameters": [
      {
        "Name": "page",
        "Type": "System.Int32",
        "IsRequired": false
      },
      {
        "Name": "pageSize",
        "Type": "System.Int32",
        "IsRequired": false
      }
    ],
    "ReturnTypes": []
  },
  {
    "ContainingType": "backend.Controllers.TouristAreaController",
    "Method": "tourist_area_user",
    "RelativePath": "api/TouristArea/tourist_area_user",
    "HttpMethod": "GET",
    "IsController": true,
    "Order": 0,
    "Parameters": [
      {
        "Name": "page",
        "Type": "System.Int32",
        "IsRequired": false
      },
      {
        "Name": "pageSize",
        "Type": "System.Int32",
        "IsRequired": false
      }
    ],
    "ReturnTypes": []
  },
  {
    "ContainingType": "backend.Controllers.TouristPlaceController",
    "Method": "CreateTouristPlace",
    "RelativePath": "api/TouristPlace",
    "HttpMethod": "POST",
    "IsController": true,
    "Order": 0,
    "Parameters": [
      {
        "Name": "req",
        "Type": "backend.DTO.TouristPlaceRequest",
        "IsRequired": true
      }
    ],
    "ReturnTypes": []
  },
  {
    "ContainingType": "backend.Controllers.TouristPlaceController",
    "Method": "UpdateTouristPlace",
    "RelativePath": "api/TouristPlace/{id}",
    "HttpMethod": "PUT",
    "IsController": true,
    "Order": 0,
    "Parameters": [
      {
        "Name": "id",
        "Type": "System.Int32",
        "IsRequired": true
      },
      {
        "Name": "req",
        "Type": "backend.DTO.TouristPlaceRequest",
        "IsRequired": true
      }
    ],
    "ReturnTypes": []
  },
  {
    "ContainingType": "backend.Controllers.TouristPlaceController",
    "Method": "DeleteTouristPlace",
    "RelativePath": "api/TouristPlace/{id}",
    "HttpMethod": "DELETE",
    "IsController": true,
    "Order": 0,
    "Parameters": [
      {
        "Name": "id",
        "Type": "System.Int32",
        "IsRequired": true
      }
    ],
    "ReturnTypes": []
  },
  {
    "ContainingType": "backend.Controllers.TouristPlaceController",
    "Method": "UpdateTouristPlaceStatus",
    "RelativePath": "api/TouristPlace/admin/{id}/status",
    "HttpMethod": "PUT",
    "IsController": true,
    "Order": 0,
    "Parameters": [
      {
        "Name": "id",
        "Type": "System.Int32",
        "IsRequired": true
      },
      {
        "Name": "req",
        "Type": "backend.DTO.ApprovalRequest",
        "IsRequired": true
      }
    ],
    "ReturnTypes": []
  },
  {
    "ContainingType": "backend.Controllers.TouristPlaceController",
    "Method": "GetAllTouristPlacesForAdmin",
    "RelativePath": "api/TouristPlace/admin/all",
    "HttpMethod": "GET",
    "IsController": true,
    "Order": 0,
    "Parameters": [
      {
        "Name": "page",
        "Type": "System.Int32",
        "IsRequired": false
      },
      {
        "Name": "pageSize",
        "Type": "System.Int32",
        "IsRequired": false
      },
      {
        "Name": "keyword",
        "Type": "System.String",
        "IsRequired": false
      },
      {
        "Name": "status",
        "Type": "System.String",
        "IsRequired": false
      }
    ],
    "ReturnTypes": []
  },
  {
    "ContainingType": "backend.Controllers.TouristPlaceController",
    "Method": "GetAllForDropdown",
    "RelativePath": "api/TouristPlace/all-dropdown",
    "HttpMethod": "GET",
    "IsController": true,
    "Order": 0,
    "Parameters": [],
    "ReturnTypes": []
  },
  {
    "ContainingType": "backend.Controllers.TouristPlaceController",
    "Method": "ApproveTouristPlace",
    "RelativePath": "api/TouristPlace/approve/{id}",
    "HttpMethod": "PUT",
    "IsController": true,
    "Order": 0,
    "Parameters": [
      {
        "Name": "id",
        "Type": "System.Int32",
        "IsRequired": true
      },
      {
        "Name": "req",
        "Type": "backend.DTO.ApprovalRequest",
        "IsRequired": true
      }
    ],
    "ReturnTypes": []
  },
  {
    "ContainingType": "backend.Controllers.TouristPlaceController",
    "Method": "GetTouristPlaceDetail",
    "RelativePath": "api/TouristPlace/detail",
    "HttpMethod": "POST",
    "IsController": true,
    "Order": 0,
    "Parameters": [
      {
        "Name": "req",
        "Type": "backend.DTO.TourismProductDetailRequest",
        "IsRequired": true
      }
    ],
    "ReturnTypes": []
  },
  {
    "ContainingType": "backend.Controllers.TouristPlaceController",
    "Method": "GetMyTouristPlaces",
    "RelativePath": "api/TouristPlace/my-places",
    "HttpMethod": "GET",
    "IsController": true,
    "Order": 0,
    "Parameters": [
      {
        "Name": "page",
        "Type": "System.Int32",
        "IsRequired": false
      },
      {
        "Name": "pageSize",
        "Type": "System.Int32",
        "IsRequired": false
      },
      {
        "Name": "keyword",
        "Type": "System.String",
        "IsRequired": false
      },
      {
        "Name": "status",
        "Type": "System.String",
        "IsRequired": false
      }
    ],
    "ReturnTypes": []
  },
  {
    "ContainingType": "backend.Controllers.TouristPlaceController",
    "Method": "TouristPlace",
    "RelativePath": "api/TouristPlace/tourist_place",
    "HttpMethod": "GET",
    "IsController": true,
    "Order": 0,
    "Parameters": [
      {
        "Name": "page",
        "Type": "System.Int32",
        "IsRequired": false
      },
      {
        "Name": "pageSize",
        "Type": "System.Int32",
        "IsRequired": false
      }
    ],
    "ReturnTypes": []
  },
  {
    "ContainingType": "backend.Controllers.UserController",
    "Method": "ChangeRole",
    "RelativePath": "api/User/change-role/{id}",
    "HttpMethod": "PUT",
    "IsController": true,
    "Order": 0,
    "Parameters": [
      {
        "Name": "id",
        "Type": "System.Guid",
        "IsRequired": true
      },
      {
        "Name": "req",
        "Type": "backend.DTO.ChangeRoleRequest",
        "IsRequired": true
      }
    ],
    "ReturnTypes": []
  },
  {
    "ContainingType": "backend.Controllers.UserController",
    "Method": "GetListUsers",
    "RelativePath": "api/User/list",
    "HttpMethod": "GET",
    "IsController": true,
    "Order": 0,
    "Parameters": [
      {
        "Name": "page",
        "Type": "System.Int32",
        "IsRequired": false
      },
      {
        "Name": "pageSize",
        "Type": "System.Int32",
        "IsRequired": false
      }
    ],
    "ReturnTypes": []
  },
  {
    "ContainingType": "backend.Controllers.UserController",
    "Method": "SubmitReport",
    "RelativePath": "api/User/reports",
    "HttpMethod": "POST",
    "IsController": true,
    "Order": 0,
    "Parameters": [
      {
        "Name": "req",
        "Type": "backend.DTO.ReportRequest",
        "IsRequired": true
      }
    ],
    "ReturnTypes": []
  },
  {
    "ContainingType": "backend.Controllers.UserController",
    "Method": "ToggleStatus",
    "RelativePath": "api/User/toggle-status/{id}",
    "HttpMethod": "PUT",
    "IsController": true,
    "Order": 0,
    "Parameters": [
      {
        "Name": "id",
        "Type": "System.Guid",
        "IsRequired": true
      }
    ],
    "ReturnTypes": []
  },
  {
    "ContainingType": "backend.Controllers.UserController",
    "Method": "UpgradeRole",
    "RelativePath": "api/User/upgrade-role",
    "HttpMethod": "PUT",
    "IsController": true,
    "Order": 0,
    "Parameters": [
      {
        "Name": "req",
        "Type": "backend.DTO.ChangeRoleRequest",
        "IsRequired": true
      }
    ],
    "ReturnTypes": []
  }
]